pihm/__init__.py
pihm/pihm_output.py
pihm/pihm_read.py
PIHM_utils-2.0.3.dist-info/LICENSE
PIHM_utils-2.0.3.dist-info/METADATA
PIHM_utils-2.0.3.dist-info/WHEEL
PIHM_utils-2.0.3.dist-info/top_level.txt
PIHM_utils-2.0.3.dist-info/RECORD
