Metadata-Version: 2.1
Name: PIHM-utils
Version: 2.0.3
Summary: Python scripts to read MM-PIHM input and output files
Home-page: https://github.com/PSUmodeling/PIHM-utils
Author: Yuning Shi
Author-email: shiyuning@gmail.com
License: MIT
Requires-Python: >=3.6
License-File: LICENSE
Requires-Dist: numpy >=1.19.5
Requires-Dist: pandas >=1.1.5
